ai/backend/appproxy/common/VERSION
ai/backend/appproxy/common/__init__.py
ai/backend/appproxy/common/config.py
ai/backend/appproxy/common/defs.py
ai/backend/appproxy/common/etcd.py
ai/backend/appproxy/common/events.py
ai/backend/appproxy/common/openapi.py
ai/backend/appproxy/common/py.typed
ai/backend/appproxy/common/types.py
ai/backend/appproxy/common/utils.py
ai/backend/appproxy/common/errors/__init__.py
ai/backend/appproxy/common/errors/config.py
ai/backend/appproxy/common/errors/http.py
ai/backend/appproxy/common/errors/service.py
ai/backend/appproxy/common/templates/error.jinja2
backend_ai_appproxy_common-26.1.0.dist-info/METADATA
backend_ai_appproxy_common-26.1.0.dist-info/WHEEL
backend_ai_appproxy_common-26.1.0.dist-info/namespace_packages.txt
backend_ai_appproxy_common-26.1.0.dist-info/top_level.txt
backend_ai_appproxy_common-26.1.0.dist-info/RECORD
