Metadata-Version: 2.4
Name: backend.ai-appproxy-common
Version: 26.1.0
Summary: Backend.AI AppProxy Common
Home-page: https://github.com/lablup/backend.ai
Author: Lablup Inc. and contributors
License: Proprietary
Project-URL: Documentation, https://docs.backend.ai/
Project-URL: Source, https://github.com/lablup/backend.ai
Classifier: Intended Audience :: Developers
Classifier: Operating System :: MacOS :: MacOS X
Classifier: Operating System :: POSIX :: Linux
Classifier: Programming Language :: Python
Classifier: Programming Language :: Python :: 3
Classifier: Environment :: No Input/Output (Daemon)
Classifier: Topic :: Scientific/Engineering
Classifier: Topic :: Software Development
Classifier: Development Status :: 5 - Production/Stable
Classifier: Programming Language :: Python :: 3.13
Requires-Python: >=3.13,<3.14
Requires-Dist: PyYAML~=6.0
Requires-Dist: aiohttp_cors~=0.8.1
Requires-Dist: aiohttp~=3.13.3
Requires-Dist: backend.ai-common==26.1.0
Requires-Dist: backend.ai-logging==26.1.0
Requires-Dist: backend.ai-plugin==26.1.0
Requires-Dist: pydantic[email]~=2.11.3
Requires-Dist: pyhumps~=3.8.0
Requires-Dist: redis[hiredis]~=7.1.0
Requires-Dist: types-PyYAML
Requires-Dist: types-redis
Dynamic: author
Dynamic: classifier
Dynamic: description
Dynamic: description-content-type
Dynamic: home-page
Dynamic: license
Dynamic: project-url
Dynamic: requires-dist
Dynamic: requires-python
Dynamic: summary
